{
  "10 et demi":{"location":"disque-dur"},
  "12 angry man":{"location":"disque-dur"},
  "127 hours":{"location":"disque-dur"},
  "1981":{"location":"disque-dur"},
  "5 days of war":{"location":"disque-dur"},
  "A single man":{"location":"disque-dur"},
  "Alice au pays des merveilles":{"location":"disque-dur"},
  "And soon the darkness":{"location":"disque-dur"},
  "Another earth":{"location":"disque-dur"},
  "Beastly":{"location":"disque-dur"},
  "Beginners":{"location":"disque-dur"},
  "Birthday girl":{"location":"disque-dur"},
  "Black death":{"location":"disque-dur"},
  "Black swan":{"location":"disque-dur"},
  "Blinde side":{"location":"disque-dur"},
  "Bridesmaids":{"location":"disque-dur"},
  "Broker sun":{"location":"disque-dur"},
  "Brooklyn's finest":{"location":"disque-dur"},
  "Buried":{"location":"disque-dur"},
  "Cars 2":{"location":"disque-dur"},
  "Case départ":{"location":"disque-dur"},
  "Casino jack":{"location":"disque-dur"},
  "Cemtry juncction":{"location":"disque-dur"},
  "Cherry":{"location":"disque-dur"},
  "Convinction":{"location":"disque-dur"},
  "Cyrus":{"location":"disque-dur"},
  "Dany boons trop stylé":{"location":"disque-dur"},
  "Date night":{"location":"disque-dur"},
  "Dear john":{"location":"disque-dur"},
  "Des hommes et des dieux":{"location":"disque-dur"},
  "Despectable me":{"location":"disque-dur"},
  "Devils playground":{"location":"disque-dur"},
  "Dikkenek":{"location":"disque-dur"},
  "Dream house":{"location":"disque-dur"},
  "Earthling":{"location":"disque-dur"},
  "Eat preay love":{"location":"disque-dur"},
  "Entre les murs":{"location":"disque-dur"},
  "Être et avoir":{"location":"disque-dur"},
  "Fadded memories":{"location":"disque-dur"},
  "Fork aver knives":{"location":"disque-dur"},
  "Gainsbourg vie héroique":{"location":"disque-dur"},
  "Get him to the greek":{"location":"disque-dur"},
  "Gnomeo et juliette":{"location":"disque-dur"},
  "Harry potter and the deatly hollow part 1":{"location":"disque-dur"},
  "Harry potter and the order of the phoenix":{"location":"disque-dur"},
  "Headhunter":{"location":"disque-dur"},
  "Hearafter":{"location":"disque-dur"},
  "Hole in one":{"location":"disque-dur"},
  "Horrible bosses":{"location":"disque-dur"},
  "Hugo":{"location":"disque-dur"},
  "Humain":{"location":"disque-dur"},
  "I am a slave":{"location":"disque-dur"},
  "Illusioniste":{"location":"disque-dur"},
  "In time":{"location":"disque-dur"},
  "Incedies":{"location":"disque-dur"},
  "Inception":{"location":"disque-dur"},
  "Inglorius bastard":{"location":"disque-dur"},
  "Inside job":{"location":"disque-dur"},
  "Invictus":{"location":"disque-dur"},
  "Iron man 2":{"location":"disque-dur"},
  "J edgar":{"location":"disque-dur"},
  "Kes":{"location":"disque-dur"},
  "Khnight and day":{"location":"disque-dur"},
  "Kick ass":{"location":"disque-dur"},
  "Killing bono":{"location":"disque-dur"},
  "King guillaume":{"location":"disque-dur"},
  "Kung fu panda":{"location":"disque-dur"},
  "Kunkytown":{"location":"disque-dur"},
  "L'appat":{"location":"disque-dur"},
  "L'arnacoeur":{"location":"disque-dur"},
  "L'homme qui volulais vivre sa vie":{"location":"disque-dur"},
  "L'immortel":{"location":"disque-dur"},
  "La bataille de passchandaele":{"location":"disque-dur"},
  "La rafle":{"location":"disque-dur"},
  "Le baiser du barbu":{"location":"disque-dur"},
  "Le bruit des glaçons":{"location":"disque-dur"},
  "Le fils de jo":{"location":"disque-dur"},
  "Le nom des gens":{"location":"disque-dur"},
  "Le petit nicolas":{"location":"disque-dur"},
  "Le secret de la licorne":{"location":"disque-dur"},
  "Le siffleur":{"location":"disque-dur"},
  "Les femmes du sixième étage":{"location":"disque-dur"},
  "Les invité de mon père":{"location":"disque-dur"},
  "Les lyonais":{"location":"disque-dur"},
  "Les pieds dans le vide":{"location":"disque-dur"},
  "Life as we know it":{"location":"disque-dur"},
  "Life in a day":{"location":"disque-dur"},
  "Limiteless":{"location":"disque-dur"},
  "London boulevard":{"location":"disque-dur"},
  "Looking for Éric":{"location":"disque-dur"},
  "Lucky":{"location":"disque-dur"},
  "Luky luke":{"location":"disque-dur"},
  "Margin call":{"location":"disque-dur"},
  "Max et les maximonstre":{"location":"disque-dur"},
  "Millenium 2":{"location":"disque-dur"},
  "Moi michel g milliardaire":{"location":"disque-dur"},
  "Moneyball":{"location":"disque-dur"},
  "Mr nobody":{"location":"disque-dur"},
  "My name is khan":{"location":"disque-dur"},
  "My own love song":{"location":"disque-dur"},
  "Ne te retourne pas":{"location":"disque-dur"},
  "Never let me go":{"location":"disque-dur"},
  "Notre jour viendra":{"location":"disque-dur"},
  "Oceans":{"location":"disque-dur"},
  "Omar ma tuer":{"location":"disque-dur"},
  "Ondine":{"location":"disque-dur"},
  "One a minute":{"location":"disque-dur"},
  "Our idot brother":{"location":"disque-dur"},
  "Passion play":{"location":"disque-dur"},
  "Paul":{"location":"disque-dur"},
  "Peacock":{"location":"disque-dur"},
  "Polisse":{"location":"disque-dur"},
  "Prince of persia the sand of time":{"location":"disque-dur"},
  "Rangoo":{"location":"disque-dur"},
  "Real steel":{"location":"disque-dur"},
  "Remember me":{"location":"disque-dur"},
  "Rio":{"location":"disque-dur"},
  "Rtt":{"location":"disque-dur"},
  "Salt":{"location":"disque-dur"},
  "Sans laisser de traces":{"location":"disque-dur"},
  "Shank":{"location":"disque-dur"},
  "Shrek forever after":{"location":"disque-dur"},
  "Shutter island":{"location":"disque-dur"},
  "Somewhere":{"location":"disque-dur"},
  "Somthing borrowed":{"location":"disque-dur"},
  "Soul surfer":{"location":"disque-dur"},
  "Stepup3":{"location":"disque-dur"},
  "Stone":{"location":"disque-dur"},
  "Sumo":{"location":"disque-dur"},
  "Super8":{"location":"disque-dur"},
  "Sur le rythme":{"location":"disque-dur"},
  "Sur les traces de tintin":{"location":"disque-dur"},
  "Textuality":{"location":"disque-dur"},
  "Tezxas killing fields":{"location":"disque-dur"},
  "Thats what i am":{"location":"disque-dur"},
  "The adjustment bureua":{"location":"disque-dur"},
  "The american":{"location":"disque-dur"},
  "The art of getting by":{"location":"disque-dur"},
  "The beaver":{"location":"disque-dur"},
  "The box":{"location":"disque-dur"},
  "The compagny men":{"location":"disque-dur"},
  "The dilemna":{"location":"disque-dur"},
  "The fighter":{"location":"disque-dur"},
  "The ghost writter":{"location":"disque-dur"},
  "The green hornet":{"location":"disque-dur"},
  "The hangover 2":{"location":"disque-dur"},
  "The hangover":{"location":"disque-dur"},
  "The help":{"location":"disque-dur"},
  "The job":{"location":"disque-dur"},
  "The killer inside me":{"location":"disque-dur"},
  "The kings speech":{"location":"disque-dur"},
  "The last airbender":{"location":"disque-dur"},
  "The last seven":{"location":"disque-dur"},
  "The leat among you":{"location":"disque-dur"},
  "The lincoln layer":{"location":"disque-dur"},
  "The man from eath":{"location":"disque-dur"},
  "The next threee days":{"location":"disque-dur"},
  "The odes of march":{"location":"disque-dur"},
  "The princess and the frog":{"location":"disque-dur"},
  "The scientiste":{"location":"disque-dur"},
  "The social network":{"location":"disque-dur"},
  "The speed of thourght":{"location":"disque-dur"},
  "The stranger":{"location":"disque-dur"},
  "The switch":{"location":"disque-dur"},
  "The town":{"location":"disque-dur"},
  "The trotsky":{"location":"disque-dur"},
  "The way back":{"location":"disque-dur"},
  "The way":{"location":"disque-dur"},
  "Therife":{"location":"disque-dur"},
  "Ticking clock":{"location":"disque-dur"},
  "Tokyo":{"location":"disque-dur"},
  "Tow story 3":{"location":"disque-dur"},
  "Transformer 2":{"location":"disque-dur"},
  "Triage":{"location":"disque-dur"},
  "Tron legacy":{"location":"disque-dur"},
  "True grift":{"location":"disque-dur"},
  "Un balcon sur mère":{"location":"disque-dur"},
  "Un monstre a paris":{"location":"disque-dur"},
  "Un poison violent":{"location":"disque-dur"},
  "Un prohète":{"location":"disque-dur"},
  "Unstoppable":{"location":"disque-dur"},
  "Unthinkable":{"location":"disque-dur"},
  "Vampires suck":{"location":"disque-dur"},
  "Venus noir":{"location":"disque-dur"},
  "Violent blue":{"location":"disque-dur"},
  "Voyage of the dawn treader":{"location":"disque-dur"},
  "Waiting forever":{"location":"disque-dur"},
  "Wall street money never sleep":{"location":"disque-dur"},
  "Water for elephants":{"location":"disque-dur"},
  "We bought a zoo":{"location":"disque-dur"},
  "Whatever works":{"location":"disque-dur"},
  "Wild target":{"location":"disque-dur"},
  "Xmen first class":{"location":"disque-dur"}
}
